[
  {
    "symbol": "NVDA",
    "name": "NVIDIA Corporation",
    "capex": -138735000,
    "year": 2024,
    "revenue": 26914000000,
    "earnings": 120067000000,
    "sector": "Technology",
    "market_cap": 4940517120000,
    "market_cap_updated": "2026-07-20T22:47:41",
    "operating_income": 130387000000,
    "gross_profit": 153463000000,
    "operating_cash_flow": 102718000000,
    "total_assets": 206803000000,
    "total_liabilities": 49510000000,
    "stockholders_equity": 157293000000,
    "long_term_debt": 8468000000,
    "cash": 10605000000,
    "rd_expense": 18497000000,
    "shares_outstanding": 24304000000,
    "free_cash_flow": 102579265000,
    "debt_to_equity": 0.05,
    "operating_margin": 484.5,
    "profit_margin": 446.1
  },
  {
    "symbol": "MSFT",
    "name": "Microsoft Corporation",
    "capex": -64551000000,
    "year": 2024,
    "revenue": 281724000000,
    "earnings": 101832000000,
    "sector": "Technology",
    "market_cap": 2990623860000,
    "market_cap_updated": "2026-07-20T22:47:42",
    "operating_income": 128528000000,
    "gross_profit": 193893000000,
    "operating_cash_flow": 136162000000,
    "total_assets": 619003000000,
    "total_liabilities": 275524000000,
    "stockholders_equity": 343479000000,
    "long_term_debt": 43151000000,
    "cash": 30242000000,
    "rd_expense": 32488000000,
    "shares_outstanding": 7434000000,
    "free_cash_flow": 71611000000,
    "debt_to_equity": 0.13,
    "operating_margin": 45.6,
    "profit_margin": 36.1
  },
  {
    "symbol": "AAPL",
    "name": "Apple Inc.",
    "capex": -12715000000,
    "year": 2024,
    "revenue": 416161000000,
    "earnings": 112010000000,
    "sector": "Technology",
    "market_cap": 4824798983400,
    "market_cap_updated": "2026-07-20T22:47:42",
    "operating_income": 133050000000,
    "gross_profit": 195201000000,
    "operating_cash_flow": 111482000000,
    "total_assets": 359241000000,
    "total_liabilities": 285508000000,
    "stockholders_equity": 73733000000,
    "long_term_debt": 90678000000,
    "cash": 35934000000,
    "rd_expense": 34550000000,
    "shares_outstanding": 14773260000,
    "free_cash_flow": 98767000000,
    "debt_to_equity": 1.23,
    "operating_margin": 32.0,
    "profit_margin": 26.9
  },
  {
    "symbol": "AMZN",
    "name": "Amazon.com Inc.",
    "capex": -6737000000,
    "year": 2024,
    "revenue": 716924000000,
    "earnings": 77670000000,
    "sector": "Consumer Discretionary",
    "market_cap": 2682642690000,
    "market_cap_updated": "2026-07-20T22:47:42",
    "operating_income": 79975000000,
    "gross_profit": 5531000000,
    "operating_cash_flow": 139514000000,
    "total_assets": 818042000000,
    "stockholders_equity": 411065000000,
    "long_term_debt": 68836000000,
    "cash": 86810000000,
    "shares_outstanding": 10731000000,
    "free_cash_flow": 132777000000,
    "debt_to_equity": 0.17,
    "operating_margin": 11.2,
    "profit_margin": 10.8
  },
  {
    "symbol": "GOOGL",
    "name": "Alphabet Inc.",
    "capex": -91447000000,
    "year": 2024,
    "revenue": 350018000000,
    "earnings": 132170000000,
    "sector": "Technology",
    "market_cap": 4254855120000,
    "market_cap_updated": "2026-07-20T22:47:42",
    "operating_income": 129039000000,
    "operating_cash_flow": 164713000000,
    "total_assets": 595281000000,
    "total_liabilities": 180016000000,
    "stockholders_equity": 415265000000,
    "long_term_debt": 49085000000,
    "cash": 30708000000,
    "rd_expense": 61087000000,
    "shares_outstanding": 12088000000,
    "free_cash_flow": 73266000000,
    "debt_to_equity": 0.12,
    "operating_margin": 36.9,
    "profit_margin": 37.8
  },
  {
    "symbol": "META",
    "name": "Meta Platforms Inc.",
    "capex": -69691000000,
    "year": 2024,
    "revenue": 200966000000,
    "earnings": 60458000000,
    "sector": "Technology",
    "market_cap": 1803926319282,
    "market_cap_updated": "2025-07-12T17:11:52.930506",
    "operating_income": 83276000000,
    "operating_cash_flow": 115800000000,
    "total_assets": 366021000000,
    "total_liabilities": 148778000000,
    "stockholders_equity": 217243000000,
    "long_term_debt": 58744000000,
    "cash": 35873000000,
    "rd_expense": 57372000000,
    "free_cash_flow": 46109000000,
    "debt_to_equity": 0.27,
    "operating_margin": 41.4,
    "profit_margin": 30.1
  },
  {
    "symbol": "AVGO",
    "name": "Broadcom Inc.",
    "capex": -623000000,
    "year": 2024,
    "revenue": 63887000000,
    "sector": "Technology",
    "market_cap": 1792856560000,
    "market_cap_updated": "2026-07-20T22:47:43",
    "earnings": 5895000000,
    "operating_income": 25484000000,
    "gross_profit": 43294000000,
    "operating_cash_flow": 27537000000,
    "total_assets": 171092000000,
    "total_liabilities": 89800000000,
    "stockholders_equity": 24941000000,
    "long_term_debt": 39665000000,
    "cash": 16178000000,
    "rd_expense": 10977000000,
    "shares_outstanding": 4741000000,
    "free_cash_flow": 26914000000,
    "debt_to_equity": 1.59,
    "operating_margin": 39.9,
    "profit_margin": 9.2
  },
  {
    "symbol": "TSLA",
    "name": "Tesla Inc.",
    "capex": -8527000000,
    "year": 2024,
    "revenue": 94827000000,
    "sector": "Consumer Discretionary",
    "market_cap": 1386257070000,
    "market_cap_updated": "2026-07-20T22:47:43",
    "earnings": 3794000000,
    "operating_income": 4355000000,
    "gross_profit": 17094000000,
    "operating_cash_flow": 14747000000,
    "total_assets": 137806000000,
    "total_liabilities": 54941000000,
    "stockholders_equity": 82137000000,
    "long_term_debt": 6584000000,
    "cash": 16513000000,
    "rd_expense": 6411000000,
    "shares_outstanding": 3751000000,
    "free_cash_flow": 6220000000,
    "debt_to_equity": 0.08,
    "operating_margin": 4.6,
    "profit_margin": 4.0
  },
  {
    "symbol": "BRK.B",
    "name": "Berkshire Hathaway Inc.",
    "capex": -15400000000,
    "year": 2024,
    "revenue": 364482000000,
    "sector": "Financials",
    "market_cap": 880000000000
  },
  {
    "symbol": "JPM",
    "name": "JPMorgan Chase & Co.",
    "capex": -4400000000,
    "year": 2024,
    "revenue": 182447000000,
    "sector": "Financials",
    "market_cap": 913661294000,
    "market_cap_updated": "2026-07-20T22:47:43",
    "earnings": 57048000000,
    "operating_cash_flow": -147782000000,
    "total_assets": 4424900000000,
    "total_liabilities": 4062462000000,
    "stockholders_equity": 362438000000,
    "long_term_debt": 267889000000,
    "cash": 278793000000,
    "shares_outstanding": 2696200000,
    "free_cash_flow": -152182000000,
    "debt_to_equity": 0.74,
    "profit_margin": 31.3
  },
  {
    "symbol": "WMT",
    "name": "Walmart Inc.",
    "capex": -26642000000,
    "year": 2024,
    "revenue": 706413000000,
    "sector": "Consumer Staples",
    "market_cap": 383499600000,
    "market_cap_updated": "2026-07-20T22:47:43",
    "earnings": 21893000000,
    "operating_income": 29825000000,
    "operating_cash_flow": 41565000000,
    "total_assets": 284668000000,
    "stockholders_equity": 99617000000,
    "long_term_debt": 38166000000,
    "cash": 10727000000,
    "shares_outstanding": 3418000000,
    "free_cash_flow": 14923000000,
    "debt_to_equity": 0.38,
    "operating_margin": 4.2,
    "profit_margin": 3.1
  },
  {
    "symbol": "LLY",
    "name": "Eli Lilly and Co.",
    "capex": -2800000000,
    "year": 2024,
    "revenue": 65179000000,
    "sector": "Healthcare",
    "market_cap": 751564125360,
    "market_cap_updated": "2025-07-12T17:11:56.684396",
    "earnings": 20640000000,
    "operating_cash_flow": 16813000000,
    "total_assets": 112476000000,
    "stockholders_equity": 26535000000,
    "long_term_debt": 29474000000,
    "cash": 7268000000,
    "rd_expense": 7190800000,
    "free_cash_flow": 14013000000,
    "debt_to_equity": 1.11,
    "profit_margin": 31.7
  },
  {
    "symbol": "V",
    "name": "Visa Inc.",
    "capex": -900000000,
    "year": 2024,
    "revenue": 40000000000,
    "sector": "Financial Services",
    "market_cap": 674691670198,
    "market_cap_updated": "2025-07-12T17:12:00.962454",
    "earnings": 20058000000,
    "operating_income": 23994000000,
    "operating_cash_flow": 23059000000,
    "total_assets": 99627000000,
    "total_liabilities": 61718000000,
    "stockholders_equity": 26437000000,
    "long_term_debt": 20977000000,
    "cash": 17164000000,
    "free_cash_flow": 22159000000,
    "debt_to_equity": 0.79,
    "operating_margin": 60.0,
    "profit_margin": 50.1
  },
  {
    "symbol": "ORCL",
    "name": "Oracle Corporation",
    "capex": -55663000000,
    "year": 2024,
    "revenue": 67357000000,
    "sector": "Technology",
    "market_cap": 349574400000,
    "market_cap_updated": "2026-07-20T22:47:44",
    "earnings": 17087000000,
    "operating_income": 20606000000,
    "gross_profit": 24287000000,
    "operating_cash_flow": 31977000000,
    "total_assets": 261759000000,
    "stockholders_equity": 42508000000,
    "long_term_debt": 0,
    "cash": 31289000000,
    "rd_expense": 10272000000,
    "shares_outstanding": 2880000000,
    "free_cash_flow": -23686000000,
    "debt_to_equity": 0.0,
    "operating_margin": 30.6,
    "profit_margin": 25.4
  },
  {
    "symbol": "NFLX",
    "name": "Netflix Inc.",
    "capex": -688220000,
    "year": 2024,
    "revenue": 45183036000,
    "sector": "Technology",
    "market_cap": 285418161340,
    "market_cap_updated": "2026-07-20T22:47:44",
    "earnings": 10981201000,
    "operating_income": 13326603000,
    "gross_profit": 2479282000,
    "operating_cash_flow": 10149273000,
    "total_assets": 55596993000,
    "total_liabilities": 28981505000,
    "stockholders_equity": 26615488000,
    "long_term_debt": 21857087000,
    "cash": 9033681000,
    "rd_expense": 3391390000,
    "shares_outstanding": 4222162150,
    "free_cash_flow": 9461053000,
    "debt_to_equity": 0.82,
    "operating_margin": 29.5,
    "profit_margin": 24.3
  },
  {
    "symbol": "XOM",
    "name": "Exxon Mobil Corporation",
    "capex": -28358000000,
    "year": 2024,
    "revenue": 276692000000,
    "sector": "Energy",
    "market_cap": 619996440000,
    "market_cap_updated": "2026-07-20T22:47:44",
    "earnings": 28844000000,
    "operating_cash_flow": 51970000000,
    "total_assets": 448980000000,
    "total_liabilities": 182354000000,
    "stockholders_equity": 259386000000,
    "long_term_debt": 23100000000,
    "cash": 10681000000,
    "rd_expense": 1200000000,
    "shares_outstanding": 4179000000,
    "free_cash_flow": 23612000000,
    "debt_to_equity": 0.09,
    "profit_margin": 10.4
  },
  {
    "symbol": "MA",
    "name": "Mastercard Inc.",
    "capex": -489000000,
    "year": 2024,
    "revenue": 29845000000,
    "sector": "Financial Services",
    "market_cap": 495856877340,
    "market_cap_updated": "2025-07-12T17:12:05.344904",
    "earnings": 3116000000,
    "operating_income": 18897000000,
    "operating_cash_flow": 17648000000,
    "total_assets": 54157000000,
    "total_liabilities": 46411000000,
    "stockholders_equity": 7737000000,
    "long_term_debt": 20000000,
    "cash": 10566000000,
    "free_cash_flow": 17159000000,
    "debt_to_equity": 0.0,
    "operating_margin": 63.3,
    "profit_margin": 10.4
  },
  {
    "symbol": "COST",
    "name": "Costco Wholesale Corp.",
    "capex": -5498000000,
    "year": 2024,
    "revenue": 275235000000,
    "sector": "Consumer Staples",
    "market_cap": 414781184600,
    "market_cap_updated": "2026-07-20T22:47:45",
    "earnings": 8099000000,
    "operating_income": 10383000000,
    "gross_profit": 16465000000,
    "operating_cash_flow": 13335000000,
    "total_assets": 77099000000,
    "total_liabilities": 47935000000,
    "stockholders_equity": 29164000000,
    "long_term_debt": 7531000000,
    "cash": 14161000000,
    "shares_outstanding": 443237000,
    "free_cash_flow": 7837000000,
    "debt_to_equity": 0.26,
    "operating_margin": 3.8,
    "profit_margin": 2.9
  },
  {
    "symbol": "JNJ",
    "name": "Johnson & Johnson",
    "capex": -4832000000,
    "year": 2024,
    "revenue": 94193000000,
    "sector": "Healthcare",
    "market_cap": 377512383000,
    "market_cap_updated": "2025-07-12T17:12:04.271261",
    "earnings": 26804000000,
    "operating_income": 21590000000,
    "gross_profit": 63937000000,
    "operating_cash_flow": 24530000000,
    "total_assets": 199210000000,
    "total_liabilities": 117666000000,
    "long_term_debt": 41438000000,
    "cash": 19709000000,
    "rd_expense": 109000000,
    "free_cash_flow": 19698000000,
    "operating_margin": 22.9,
    "profit_margin": 28.5
  },
  {
    "symbol": "PG",
    "name": "Procter & Gamble Co.",
    "capex": -3773000000,
    "year": 2024,
    "revenue": 84284000000,
    "sector": "Consumer Staples",
    "market_cap": 368210007000,
    "market_cap_updated": "2025-07-12T17:12:08.843698",
    "earnings": 15974000000,
    "operating_income": 20451000000,
    "operating_cash_flow": 17817000000,
    "total_assets": 125231000000,
    "total_liabilities": 72946000000,
    "long_term_debt": 23129000000,
    "cash": 4239000000,
    "rd_expense": 2100000000,
    "free_cash_flow": 14044000000,
    "operating_margin": 24.3,
    "profit_margin": 19.0
  },
  {
    "symbol": "HD",
    "name": "Home Depot Inc.",
    "capex": -2800000000,
    "year": 2024,
    "revenue": 164683000000,
    "sector": "Consumer Discretionary",
    "market_cap": 331707840000,
    "market_cap_updated": "2026-07-20T22:47:45",
    "earnings": 14156000000,
    "operating_income": 20890000000,
    "gross_profit": 54865000000,
    "operating_cash_flow": 16325000000,
    "total_assets": 105095000000,
    "total_liabilities": 92282000000,
    "stockholders_equity": 12813000000,
    "long_term_debt": 49397000000,
    "cash": 1389000000,
    "shares_outstanding": 996000000,
    "free_cash_flow": 13525000000,
    "debt_to_equity": 3.86,
    "operating_margin": 12.7,
    "profit_margin": 8.6
  },
  {
    "symbol": "BAC",
    "name": "Bank of America Corp",
    "capex": -3200000000,
    "year": 2024,
    "revenue": 113097000000,
    "sector": "Financials",
    "market_cap": 435777095724,
    "market_cap_updated": "2026-07-20T22:47:45",
    "earnings": 30509000000,
    "operating_cash_flow": 12613000000,
    "total_assets": 3411738000000,
    "total_liabilities": 3108495000000,
    "stockholders_equity": 303243000000,
    "long_term_debt": 317816000000,
    "cash": 161560000000,
    "shares_outstanding": 7212464345,
    "free_cash_flow": 9413000000,
    "debt_to_equity": 1.05,
    "profit_margin": 27.0
  },
  {
    "symbol": "ABBV",
    "name": "AbbVie Inc.",
    "capex": -1214000000,
    "year": 2024,
    "revenue": 61160000000,
    "sector": "Healthcare",
    "market_cap": 339943680000,
    "market_cap_updated": "2025-07-12T17:12:12.079080",
    "earnings": 4226000000,
    "operating_income": 15075000000,
    "gross_profit": 12066000000,
    "operating_cash_flow": 19030000000,
    "total_assets": 133960000000,
    "stockholders_equity": -3270000000,
    "long_term_debt": 64503000000,
    "cash": 5229000000,
    "free_cash_flow": 17816000000,
    "debt_to_equity": 20.1,
    "operating_margin": 24.6,
    "profit_margin": 6.9
  },
  {
    "symbol": "KO",
    "name": "Coca-Cola Co.",
    "capex": -2112000000,
    "year": 2024,
    "revenue": 47941000000,
    "sector": "Consumer Staples",
    "market_cap": 300739344900,
    "market_cap_updated": "2025-07-12T17:12:14.247086",
    "earnings": 13107000000,
    "operating_income": 13762000000,
    "gross_profit": 29544000000,
    "operating_cash_flow": 7408000000,
    "total_assets": 104816000000,
    "stockholders_equity": 32169000000,
    "long_term_debt": 37507000000,
    "cash": 10270000000,
    "free_cash_flow": 5296000000,
    "debt_to_equity": 1.17,
    "operating_margin": 28.7,
    "profit_margin": 27.3
  },
  {
    "symbol": "PM",
    "name": "Philip Morris International Inc.",
    "capex": -1569000000,
    "year": 2024,
    "revenue": 40648000000,
    "sector": "Consumer Staples",
    "market_cap": 347239714192,
    "market_cap_updated": "2026-07-20T22:47:46",
    "earnings": 11348000000,
    "operating_income": 14892000000,
    "gross_profit": 27282000000,
    "operating_cash_flow": 12233000000,
    "total_assets": 69185000000,
    "total_liabilities": 77213000000,
    "stockholders_equity": -9994000000,
    "long_term_debt": 17034000000,
    "cash": 4872000000,
    "rd_expense": 756000000,
    "shares_outstanding": 1801783490,
    "free_cash_flow": 10664000000,
    "operating_margin": 36.6,
    "profit_margin": 27.9
  },
  {
    "symbol": "UNH",
    "name": "UnitedHealth Group Inc.",
    "capex": -3622000000,
    "year": 2024,
    "revenue": 447567000000,
    "sector": "Healthcare",
    "market_cap": 381924300000,
    "market_cap_updated": "2026-07-20T22:47:46",
    "earnings": 12056000000,
    "operating_income": 18964000000,
    "operating_cash_flow": 19697000000,
    "total_assets": 309581000000,
    "total_liabilities": 207883000000,
    "stockholders_equity": 32454000000,
    "long_term_debt": 72320000000,
    "cash": 24365000000,
    "shares_outstanding": 906000000,
    "free_cash_flow": 16075000000,
    "debt_to_equity": 2.23,
    "operating_margin": 4.2,
    "profit_margin": 2.7
  },
  {
    "symbol": "GE",
    "name": "General Electric Co.",
    "capex": -1371000000,
    "year": 2024,
    "revenue": 9879000000,
    "sector": "Industrials",
    "market_cap": 357944075392,
    "market_cap_updated": "2026-07-20T22:47:46",
    "earnings": 8704000000,
    "operating_income": 22887000000,
    "gross_profit": 7027000000,
    "operating_cash_flow": 8537000000,
    "total_assets": 130169000000,
    "total_liabilities": 111271000000,
    "stockholders_equity": 18677000000,
    "long_term_debt": 20469000000,
    "cash": 43299000000,
    "rd_expense": 1580000000,
    "shares_outstanding": 1048766702,
    "free_cash_flow": 7166000000,
    "debt_to_equity": 1.1,
    "operating_margin": 231.7,
    "profit_margin": 88.1
  },
  {
    "symbol": "CVX",
    "name": "Chevron Corporation",
    "capex": -14700000000,
    "year": 2024,
    "revenue": 184432000000,
    "sector": "Energy",
    "market_cap": 271231830900,
    "market_cap_updated": "2025-07-12T17:12:13.169438",
    "earnings": 12299000000,
    "operating_cash_flow": 33939000000,
    "total_assets": 324012000000,
    "total_liabilities": 131836000000,
    "stockholders_equity": 186450000000,
    "long_term_debt": 25676000000,
    "cash": 8178000000,
    "rd_expense": 427000000,
    "free_cash_flow": 19239000000,
    "debt_to_equity": 0.14,
    "profit_margin": 6.7
  },
  {
    "symbol": "CSCO",
    "name": "Cisco Systems Inc.",
    "capex": -905000000,
    "year": 2024,
    "revenue": 56654000000,
    "sector": "Technology",
    "market_cap": 438372000000,
    "market_cap_updated": "2026-07-20T22:47:47",
    "earnings": 10180000000,
    "operating_income": 11760000000,
    "gross_profit": 36790000000,
    "operating_cash_flow": 14193000000,
    "total_assets": 122291000000,
    "total_liabilities": 75448000000,
    "stockholders_equity": 46843000000,
    "long_term_debt": 24611000000,
    "cash": 8346000000,
    "rd_expense": 9300000000,
    "shares_outstanding": 3960000000,
    "free_cash_flow": 13288000000,
    "debt_to_equity": 0.53,
    "operating_margin": 20.8,
    "profit_margin": 18.0
  },
  {
    "symbol": "WFC",
    "name": "Wells Fargo & Co.",
    "capex": -3500000000,
    "year": 2024,
    "revenue": 85063000000,
    "sector": "Financials",
    "market_cap": 266984158000,
    "market_cap_updated": "2026-07-20T22:47:47",
    "earnings": 21338000000,
    "operating_cash_flow": -19001000000,
    "total_assets": 2148631000000,
    "total_liabilities": 1965593000000,
    "stockholders_equity": 181117000000,
    "long_term_debt": 174712000000,
    "free_cash_flow": -22501000000,
    "debt_to_equity": 0.96,
    "profit_margin": 25.1,
    "shares_outstanding": 3092600000
  },
  {
    "symbol": "IBM",
    "name": "International Business Machines Corp",
    "capex": -1091000000,
    "year": 2024,
    "revenue": 67535000000,
    "sector": "Technology",
    "market_cap": 199570803477,
    "market_cap_updated": "2026-07-20T22:47:47",
    "earnings": 10593000000,
    "gross_profit": 39297000000,
    "operating_cash_flow": 13193000000,
    "total_assets": 151880000000,
    "total_liabilities": 119139000000,
    "stockholders_equity": 32648000000,
    "long_term_debt": 42656000000,
    "cash": 13587000000,
    "rd_expense": 8316000000,
    "shares_outstanding": 936952129,
    "free_cash_flow": 12102000000,
    "debt_to_equity": 1.31,
    "profit_margin": 15.7
  },
  {
    "symbol": "CRM",
    "name": "Salesforce Inc.",
    "capex": -594000000,
    "year": 2024,
    "revenue": 41525000000,
    "sector": "Technology",
    "market_cap": 161450910000,
    "market_cap_updated": "2026-07-20T22:47:48",
    "earnings": 7457000000,
    "operating_income": 8331000000,
    "gross_profit": 32255000000,
    "operating_cash_flow": 14996000000,
    "total_assets": 112305000000,
    "total_liabilities": 53163000000,
    "stockholders_equity": 59142000000,
    "long_term_debt": 14439000000,
    "cash": 7327000000,
    "rd_expense": 5993000000,
    "shares_outstanding": 929000000,
    "free_cash_flow": 14402000000,
    "debt_to_equity": 0.24,
    "operating_margin": 20.1,
    "profit_margin": 18.0
  },
  {
    "symbol": "AMD",
    "name": "Advanced Micro Devices Inc.",
    "capex": -974000000,
    "year": 2024,
    "revenue": 34639000000,
    "sector": "Technology",
    "market_cap": 820819100000,
    "market_cap_updated": "2026-07-20T22:47:48",
    "earnings": 4335000000,
    "operating_income": 3694000000,
    "gross_profit": 17152000000,
    "operating_cash_flow": 7709000000,
    "total_assets": 76926000000,
    "stockholders_equity": 62999000000,
    "long_term_debt": 1000000,
    "cash": 5539000000,
    "rd_expense": 8091000000,
    "shares_outstanding": 1630000000,
    "free_cash_flow": 6735000000,
    "debt_to_equity": 0.0,
    "operating_margin": 10.7,
    "profit_margin": 12.5
  },
  {
    "symbol": "ABT",
    "name": "Abbott Laboratories",
    "capex": -2171000000,
    "year": 2024,
    "revenue": 44328000000,
    "sector": "Healthcare",
    "market_cap": 229693676800,
    "market_cap_updated": "2025-07-12T17:12:31.537203",
    "earnings": 6524000000,
    "operating_income": 8053000000,
    "gross_profit": 4397000000,
    "operating_cash_flow": 9566000000,
    "total_assets": 86713000000,
    "stockholders_equity": 52130000000,
    "long_term_debt": 12929000000,
    "cash": 8522000000,
    "rd_expense": 2942000000,
    "free_cash_flow": 7395000000,
    "debt_to_equity": 0.25,
    "operating_margin": 18.2,
    "profit_margin": 14.7
  },
  {
    "symbol": "MS",
    "name": "Morgan Stanley",
    "capex": -1900000000,
    "year": 2024,
    "revenue": 34275000000,
    "sector": "Financials",
    "market_cap": 333883032858,
    "market_cap_updated": "2026-07-20T22:47:48",
    "earnings": 16861000000,
    "operating_cash_flow": -17889000000,
    "total_assets": 1420270000000,
    "total_liabilities": 1307618000000,
    "stockholders_equity": 111632000000,
    "long_term_debt": 341681000000,
    "cash": 111695000000,
    "shares_outstanding": 1582834137,
    "free_cash_flow": -19789000000,
    "debt_to_equity": 3.06,
    "profit_margin": 49.2
  },
  {
    "symbol": "AXP",
    "name": "American Express Co.",
    "capex": -2425000000,
    "year": 2024,
    "revenue": 41304000000,
    "sector": "Financial Services",
    "market_cap": 241423980000,
    "market_cap_updated": "2026-07-20T22:47:48",
    "earnings": 10833000000,
    "operating_income": 2841000000,
    "operating_cash_flow": 18428000000,
    "total_assets": 300052000000,
    "total_liabilities": 266578000000,
    "stockholders_equity": 33474000000,
    "long_term_debt": 56387000000,
    "cash": 654000000,
    "shares_outstanding": 686000000,
    "free_cash_flow": 16003000000,
    "debt_to_equity": 1.68,
    "operating_margin": 6.9,
    "profit_margin": 26.2
  },
  {
    "symbol": "LIN",
    "name": "Linde PLC",
    "capex": -5261000000,
    "year": 2024,
    "revenue": 33986000000,
    "sector": "Materials",
    "market_cap": 260470044091,
    "market_cap_updated": "2026-07-20T22:47:49",
    "earnings": 6898000000,
    "operating_income": 8923000000,
    "operating_cash_flow": 10350000000,
    "total_assets": 86817000000,
    "total_liabilities": 47076000000,
    "stockholders_equity": 38245000000,
    "long_term_debt": 22479000000,
    "cash": 5056000000,
    "rd_expense": 147000000,
    "shares_outstanding": 508680879,
    "free_cash_flow": 5089000000,
    "debt_to_equity": 0.59,
    "operating_margin": 26.3,
    "profit_margin": 20.3
  },
  {
    "symbol": "GS",
    "name": "Goldman Sachs Group Inc.",
    "capex": -2064000000,
    "year": 2024,
    "revenue": 46900000000,
    "sector": "Financials",
    "market_cap": 312791857112,
    "market_cap_updated": "2026-07-20T22:47:49",
    "earnings": 17176000000,
    "operating_cash_flow": -45154000000,
    "total_assets": 1809320000000,
    "total_liabilities": 1684348000000,
    "stockholders_equity": 124972000000,
    "long_term_debt": 236027000000,
    "cash": 164259000000,
    "shares_outstanding": 296476742,
    "free_cash_flow": -47218000000,
    "debt_to_equity": 1.89,
    "profit_margin": 36.6
  },
  {
    "symbol": "DIS",
    "name": "Walt Disney Co.",
    "capex": -8024000000,
    "year": 2024,
    "revenue": 94425000000,
    "sector": "Consumer Discretionary",
    "market_cap": 183179000000,
    "market_cap_updated": "2026-07-20T22:47:49",
    "earnings": 12404000000,
    "operating_income": 17551000000,
    "total_assets": 197514000000,
    "stockholders_equity": 109869000000,
    "long_term_debt": 42026000000,
    "cash": 5695000000,
    "shares_outstanding": 1900000000,
    "debt_to_equity": 0.38,
    "operating_margin": 18.6,
    "profit_margin": 13.1,
    "operating_cash_flow": 18101000000,
    "free_cash_flow": 10077000000
  },
  {
    "symbol": "MCD",
    "name": "McDonald's Corp.",
    "capex": -3365000000,
    "year": 2024,
    "revenue": 26885000000,
    "sector": "Consumer Discretionary",
    "market_cap": 214445547030,
    "market_cap_updated": "2025-07-12T17:12:17.465722",
    "earnings": 8563000000,
    "operating_income": 12393000000,
    "operating_cash_flow": 10551000000,
    "total_assets": 59515000000,
    "stockholders_equity": -1791000000,
    "long_term_debt": 39973000000,
    "cash": 774000000,
    "free_cash_flow": 7186000000,
    "operating_margin": 46.1,
    "profit_margin": 31.9
  },
  {
    "symbol": "TXN",
    "name": "Texas Instruments Inc.",
    "capex": -4550000000,
    "year": 2024,
    "revenue": 17682000000,
    "sector": "Technology",
    "market_cap": 200999430000,
    "market_cap_updated": "2025-07-12T17:12:30.451019",
    "earnings": 5001000000,
    "operating_income": 6023000000,
    "gross_profit": 10083000000,
    "operating_cash_flow": 7153000000,
    "total_assets": 34585000000,
    "total_liabilities": 18312000000,
    "stockholders_equity": 16273000000,
    "long_term_debt": 14048000000,
    "cash": 3225000000,
    "rd_expense": 2083000000,
    "free_cash_flow": 2603000000,
    "debt_to_equity": 0.86,
    "operating_margin": 34.1,
    "profit_margin": 28.3
  },
  {
    "symbol": "RTX",
    "name": "Raytheon Technologies Corp.",
    "capex": -2627000000,
    "year": 2024,
    "revenue": 88603000000,
    "sector": "Industrials",
    "market_cap": 268657748,
    "market_cap_updated": "2026-07-20T22:47:50",
    "earnings": 6732000000,
    "operating_income": 9300000000,
    "gross_profit": 2153000000,
    "operating_cash_flow": 10567000000,
    "total_assets": 171079000000,
    "total_liabilities": 103941000000,
    "stockholders_equity": 65245000000,
    "long_term_debt": 41078000000,
    "cash": 7435000000,
    "rd_expense": 2807000000,
    "shares_outstanding": 1381700,
    "free_cash_flow": 7940000000,
    "debt_to_equity": 0.63,
    "operating_margin": 10.5,
    "profit_margin": 7.6
  },
  {
    "symbol": "NOW",
    "name": "ServiceNow Inc.",
    "capex": -868000000,
    "year": 2024,
    "revenue": 13278000000,
    "sector": "Technology",
    "market_cap": 109650006600,
    "market_cap_updated": "2026-07-20T22:47:50",
    "earnings": 1748000000,
    "operating_income": 1824000000,
    "gross_profit": 10295000000,
    "operating_cash_flow": 5444000000,
    "total_assets": 26038000000,
    "total_liabilities": 13074000000,
    "stockholders_equity": 12964000000,
    "cash": 3726000000,
    "rd_expense": 2960000000,
    "shares_outstanding": 1047278000,
    "free_cash_flow": 4576000000,
    "operating_margin": 13.7,
    "profit_margin": 13.2
  },
  {
    "symbol": "T",
    "name": "AT&T Inc.",
    "capex": -20647000000,
    "year": 2024,
    "revenue": 125648000000,
    "sector": "Telecommunications",
    "market_cap": 194065332000,
    "market_cap_updated": "2025-07-12T17:12:44.693073",
    "earnings": 21953000000,
    "operating_income": 24162000000,
    "operating_cash_flow": 40284000000,
    "total_assets": 420198000000,
    "total_liabilities": 279032000000,
    "long_term_debt": 134718000000,
    "cash": 18234000000,
    "free_cash_flow": 19637000000,
    "operating_margin": 19.2,
    "profit_margin": 17.5
  },
  {
    "symbol": "ACN",
    "name": "Accenture PLC",
    "capex": -600039000,
    "year": 2024,
    "revenue": 69672977000,
    "sector": "Technology",
    "market_cap": 191217203580,
    "market_cap_updated": "2025-07-12T17:12:22.855229",
    "earnings": 7678433000,
    "operating_income": 10225664000,
    "operating_cash_flow": 11474399000,
    "total_assets": 65394897000,
    "stockholders_equity": 31195446000,
    "cash": 11478729000,
    "rd_expense": 817300000,
    "free_cash_flow": 10874360000,
    "operating_margin": 14.7,
    "profit_margin": 11.0
  },
  {
    "symbol": "CAT",
    "name": "Caterpillar Inc.",
    "capex": -2821000000,
    "year": 2024,
    "revenue": 67589000000,
    "sector": "Industrials",
    "market_cap": 402158790000,
    "market_cap_updated": "2026-07-20T22:47:50",
    "earnings": 2700000000,
    "operating_income": 11151000000,
    "gross_profit": 2786000000,
    "operating_cash_flow": 11739000000,
    "total_assets": 98585000000,
    "total_liabilities": 77267000000,
    "long_term_debt": 30696000000,
    "cash": 9980000000,
    "rd_expense": 2148000000,
    "shares_outstanding": 465300000,
    "free_cash_flow": 8918000000,
    "operating_margin": 16.5,
    "profit_margin": 4.0
  },
  {
    "symbol": "PEP",
    "name": "PepsiCo Inc.",
    "capex": -4700000000,
    "year": 2024,
    "revenue": 93925000000,
    "sector": "Consumer Staples",
    "market_cap": 185452280800,
    "market_cap_updated": "2025-07-12T17:12:16.396628",
    "earnings": 8240000000,
    "operating_income": 11498000000,
    "gross_profit": 50859000000,
    "operating_cash_flow": 12087000000,
    "total_assets": 107399000000,
    "total_liabilities": 86852000000,
    "stockholders_equity": 20406000000,
    "long_term_debt": 46351000000,
    "cash": 9159000000,
    "rd_expense": 839000000,
    "free_cash_flow": 7387000000,
    "debt_to_equity": 2.27,
    "operating_margin": 12.2,
    "profit_margin": 8.8
  },
  {
    "symbol": "ISRG",
    "name": "Intuitive Surgical Inc.",
    "capex": -800000000,
    "year": 2024,
    "revenue": 10064700000,
    "sector": "Healthcare",
    "market_cap": 125410667000,
    "market_cap_updated": "2026-07-20T22:47:51",
    "earnings": 2856000000,
    "operating_income": 2945500000,
    "gross_profit": 6642300000,
    "operating_cash_flow": 3030500000,
    "total_assets": 20458700000,
    "total_liabilities": 2517000000,
    "stockholders_equity": 17824000000,
    "cash": 3368000000,
    "rd_expense": 1311800000,
    "shares_outstanding": 355100000,
    "free_cash_flow": 2230500000,
    "operating_margin": 29.3,
    "profit_margin": 28.4
  },
  {
    "symbol": "VZ",
    "name": "Verizon Communications Inc.",
    "capex": -18800000000,
    "year": 2024,
    "revenue": 138191000000,
    "sector": "Telecommunications",
    "market_cap": 175480741200,
    "market_cap_updated": "2025-07-12T17:12:33.701712",
    "earnings": 17174000000,
    "operating_income": 29259000000,
    "operating_cash_flow": 37137000000,
    "total_assets": 404258000000,
    "long_term_debt": 93144000000,
    "cash": 19048000000,
    "free_cash_flow": 18337000000,
    "operating_margin": 21.2,
    "profit_margin": 12.4
  },
  {
    "symbol": "QCOM",
    "name": "Qualcomm Inc.",
    "capex": -900000000,
    "year": 2024,
    "revenue": 44284000000,
    "sector": "Technology",
    "market_cap": 182923680000,
    "market_cap_updated": "2026-07-20T22:47:51",
    "earnings": 5541000000,
    "operating_income": 12355000000,
    "operating_cash_flow": 14012000000,
    "total_assets": 50143000000,
    "total_liabilities": 28937000000,
    "stockholders_equity": 4909000000,
    "long_term_debt": 14811000000,
    "cash": 5520000000,
    "rd_expense": 9042000000,
    "shares_outstanding": 1074000000,
    "free_cash_flow": 13112000000,
    "debt_to_equity": 3.02,
    "operating_margin": 27.9,
    "profit_margin": 12.5
  },
  {
    "symbol": "BA",
    "name": "Boeing Co.",
    "capex": -2942000000,
    "year": 2024,
    "revenue": 76559000000,
    "sector": "Industrials",
    "market_cap": 212048467587,
    "market_cap_updated": "2026-07-20T22:47:51",
    "earnings": 2235000000,
    "operating_income": 4281000000,
    "gross_profit": 4289000000,
    "operating_cash_flow": 1065000000,
    "total_assets": 168235000000,
    "total_liabilities": 162778000000,
    "stockholders_equity": 5454000000,
    "long_term_debt": 53848000000,
    "cash": 10921000000,
    "rd_expense": 3615000000,
    "shares_outstanding": 1012261159,
    "free_cash_flow": -1877000000,
    "operating_margin": 5.6,
    "profit_margin": 2.9,
    "debt_to_equity": 9.87
  },
  {
    "symbol": "BLK",
    "name": "BlackRock Inc.",
    "capex": -375000000,
    "year": 2024,
    "revenue": 24216000000,
    "sector": "Financials",
    "market_cap": 163459963842,
    "market_cap_updated": "2026-07-20T22:47:52",
    "earnings": 5553000000,
    "operating_income": 7045000000,
    "operating_cash_flow": 3927000000,
    "total_assets": 169998000000,
    "total_liabilities": 108456000000,
    "stockholders_equity": 55888000000,
    "long_term_debt": 12768000000,
    "cash": 11468000000,
    "shares_outstanding": 155069171,
    "free_cash_flow": 3552000000,
    "debt_to_equity": 0.23,
    "operating_margin": 29.1,
    "profit_margin": 22.9
  },
  {
    "symbol": "TMO",
    "name": "Thermo Fisher Scientific Inc.",
    "capex": -1525000000,
    "year": 2024,
    "revenue": 44556000000,
    "sector": "Healthcare",
    "market_cap": 164157040840,
    "market_cap_updated": "2025-07-12T17:12:23.935932",
    "earnings": 6704000000,
    "operating_income": 7746000000,
    "gross_profit": 3035000000,
    "operating_cash_flow": 7818000000,
    "total_assets": 110343000000,
    "stockholders_equity": 53407000000,
    "long_term_debt": 39172000000,
    "cash": 9852000000,
    "rd_expense": 1397000000,
    "free_cash_flow": 6293000000,
    "debt_to_equity": 0.73,
    "operating_margin": 17.4,
    "profit_margin": 15.0
  },
  {
    "symbol": "C",
    "name": "Citigroup Inc.",
    "capex": -6520000000,
    "year": 2024,
    "revenue": 85225000000,
    "sector": "Financials",
    "market_cap": 161988222900,
    "market_cap_updated": "2025-07-12T17:12:58.826751",
    "earnings": 14306000000,
    "operating_cash_flow": -67632000000,
    "total_assets": 2657202000000,
    "total_liabilities": 2443380000000,
    "stockholders_equity": 212291000000,
    "long_term_debt": 315827000000,
    "cash": 188105000000,
    "free_cash_flow": -74152000000,
    "debt_to_equity": 1.49,
    "profit_margin": 16.8
  },
  {
    "symbol": "SPGI",
    "name": "S&P Global Inc.",
    "capex": -68526000,
    "year": 2024,
    "revenue": 15336000000,
    "sector": "Financials",
    "market_cap": 133966980000,
    "market_cap_updated": "2026-07-20T22:47:52",
    "earnings": 4471000000,
    "operating_income": 6478000000,
    "operating_cash_flow": 5651000000,
    "total_assets": 61200000000,
    "total_liabilities": 25048000000,
    "stockholders_equity": 31127000000,
    "long_term_debt": 13088000000,
    "cash": 1745000000,
    "shares_outstanding": 298800000,
    "free_cash_flow": 5582474000,
    "debt_to_equity": 0.42,
    "operating_margin": 42.2,
    "profit_margin": 29.2
  },
  {
    "symbol": "AMGN",
    "name": "Amgen Inc.",
    "capex": -1858000000,
    "year": 2024,
    "revenue": 36751000000,
    "sector": "Healthcare",
    "market_cap": 196214796000,
    "market_cap_updated": "2026-07-20T22:47:52",
    "earnings": 7711000000,
    "operating_income": 9080000000,
    "gross_profit": 4737000000,
    "operating_cash_flow": 9958000000,
    "total_assets": 90586000000,
    "stockholders_equity": 8658000000,
    "long_term_debt": 54604000000,
    "cash": 9129000000,
    "shares_outstanding": 538800000,
    "free_cash_flow": 8100000000,
    "debt_to_equity": 6.31,
    "operating_margin": 24.7,
    "profit_margin": 21.0
  },
  {
    "symbol": "ADBE",
    "name": "Adobe Inc.",
    "capex": -179000000,
    "year": 2024,
    "revenue": 23769000000,
    "sector": "Technology",
    "market_cap": 96947620000,
    "market_cap_updated": "2026-07-20T22:47:52",
    "earnings": 7130000000,
    "operating_income": 8706000000,
    "gross_profit": 21218000000,
    "operating_cash_flow": 10031000000,
    "total_assets": 29496000000,
    "total_liabilities": 17873000000,
    "stockholders_equity": 11623000000,
    "long_term_debt": 6210000000,
    "cash": 5431000000,
    "shares_outstanding": 413000000,
    "free_cash_flow": 9852000000,
    "debt_to_equity": 0.53,
    "operating_margin": 36.6,
    "profit_margin": 30.0
  },
  {
    "symbol": "NEE",
    "name": "NextEra Energy Inc.",
    "capex": -13400000000,
    "year": 2024,
    "revenue": 14256000000,
    "sector": "Utilities",
    "market_cap": 183304000000,
    "market_cap_updated": "2026-07-20T22:47:53",
    "earnings": 6835000000,
    "operating_income": 8280000000,
    "operating_cash_flow": 12485000000,
    "total_assets": 212721000000,
    "total_liabilities": 146242000000,
    "stockholders_equity": 54608000000,
    "long_term_debt": 89556000000,
    "cash": 2812000000,
    "shares_outstanding": 2083000000,
    "free_cash_flow": -915000000,
    "debt_to_equity": 1.64,
    "operating_margin": 58.1,
    "profit_margin": 47.9
  },
  {
    "symbol": "HON",
    "name": "Honeywell International Inc.",
    "capex": -986000000,
    "year": 2024,
    "revenue": 37442000000,
    "sector": "Industrials",
    "market_cap": 143692154000,
    "market_cap_updated": "2026-07-20T22:47:53",
    "earnings": 4729000000,
    "operating_income": 8127000000,
    "gross_profit": 3470000000,
    "operating_cash_flow": 6408000000,
    "total_assets": 73681000000,
    "stockholders_equity": 13904000000,
    "long_term_debt": 29046000000,
    "cash": 12487000000,
    "rd_expense": 1812000000,
    "shares_outstanding": 635300000,
    "free_cash_flow": 5422000000,
    "debt_to_equity": 2.09,
    "operating_margin": 21.7,
    "profit_margin": 12.6
  },
  {
    "symbol": "DHR",
    "name": "Danaher Corp.",
    "capex": -1156000000,
    "year": 2024,
    "revenue": 24568000000,
    "sector": "Healthcare",
    "market_cap": 142164659000,
    "market_cap_updated": "2026-07-20T22:47:53",
    "earnings": 3614000000,
    "operating_income": 4690000000,
    "gross_profit": 14523000000,
    "operating_cash_flow": 6416000000,
    "total_assets": 83464000000,
    "total_liabilities": 8444400000,
    "stockholders_equity": 52534000000,
    "long_term_debt": 18418000000,
    "cash": 19912300000,
    "rd_expense": 1598000000,
    "shares_outstanding": 706900000,
    "free_cash_flow": 5260000000,
    "debt_to_equity": 0.35,
    "operating_margin": 19.1,
    "profit_margin": 14.7
  },
  {
    "symbol": "PFE",
    "name": "Pfizer Inc.",
    "capex": -2629000000,
    "year": 2024,
    "revenue": 50914000000,
    "sector": "Healthcare",
    "market_cap": 145829740500,
    "market_cap_updated": "2025-07-12T17:12:39.175270",
    "earnings": 7771000000,
    "operating_cash_flow": 11704000000,
    "total_assets": 208160000000,
    "total_liabilities": 121385000000,
    "stockholders_equity": 86476000000,
    "long_term_debt": 4000000000,
    "cash": 1142000000,
    "free_cash_flow": 9075000000,
    "debt_to_equity": 0.05,
    "profit_margin": 15.3
  },
  {
    "symbol": "COF",
    "name": "Capital One Financial Corp.",
    "capex": -1578000000,
    "year": 2024,
    "revenue": 8062000000,
    "sector": "Financials",
    "market_cap": 129252396574,
    "market_cap_updated": "2026-07-20T22:47:53",
    "earnings": 2453000000,
    "operating_cash_flow": 27718000000,
    "total_assets": 669009000000,
    "total_liabilities": 555393000000,
    "stockholders_equity": 113616000000,
    "long_term_debt": 31377000000,
    "shares_outstanding": 625102271,
    "free_cash_flow": 26140000000,
    "debt_to_equity": 0.28,
    "profit_margin": 30.4
  },
  {
    "symbol": "UNP",
    "name": "Union Pacific Corp.",
    "capex": -3791000000,
    "year": 2024,
    "revenue": 24510000000,
    "sector": "Industrials",
    "market_cap": 175749093135,
    "market_cap_updated": "2026-07-20T22:47:54",
    "earnings": 7138000000,
    "operating_income": 9846000000,
    "operating_cash_flow": 9290000000,
    "total_assets": 69698000000,
    "total_liabilities": 51231000000,
    "stockholders_equity": 18467000000,
    "long_term_debt": 31814000000,
    "cash": 1266000000,
    "shares_outstanding": 593245884,
    "free_cash_flow": 5499000000,
    "debt_to_equity": 1.72,
    "operating_margin": 40.2,
    "profit_margin": 29.1
  },
  {
    "symbol": "DE",
    "name": "Deere & Co.",
    "capex": -1360000000,
    "year": 2024,
    "revenue": 45684000000,
    "sector": "Industrials",
    "market_cap": 158454400000,
    "market_cap_updated": "2026-07-20T22:47:54",
    "earnings": 5027000000,
    "operating_income": 9039000000,
    "gross_profit": 2189000000,
    "operating_cash_flow": 7459000000,
    "total_assets": 105996000000,
    "total_liabilities": 79989000000,
    "stockholders_equity": 25950000000,
    "long_term_debt": 32888000000,
    "cash": 8276000000,
    "rd_expense": 2311000000,
    "shares_outstanding": 270400000,
    "free_cash_flow": 6099000000,
    "debt_to_equity": 1.27,
    "operating_margin": 19.8,
    "profit_margin": 11.0
  },
  {
    "symbol": "TJX",
    "name": "TJX Companies Inc.",
    "capex": -1957000000,
    "year": 2024,
    "revenue": 29078407000,
    "sector": "Consumer Discretionary",
    "market_cap": 172373600198,
    "market_cap_updated": "2026-07-20T22:47:54",
    "earnings": 5494000000,
    "operating_income": 4763227000,
    "gross_profit": 3060635000,
    "operating_cash_flow": 6874000000,
    "total_assets": 35767000000,
    "stockholders_equity": 10190000000,
    "long_term_debt": 1870000000,
    "cash": 6230000000,
    "shares_outstanding": 1107087991,
    "free_cash_flow": 4917000000,
    "debt_to_equity": 0.18,
    "operating_margin": 16.4,
    "profit_margin": 18.9
  },
  {
    "symbol": "GILD",
    "name": "Gilead Sciences Inc.",
    "capex": -563000000,
    "year": 2024,
    "revenue": 29443000000,
    "sector": "Healthcare",
    "market_cap": 165313610000,
    "market_cap_updated": "2026-07-20T22:47:54",
    "earnings": 8510000000,
    "operating_income": 10022000000,
    "gross_profit": 5930000000,
    "operating_cash_flow": 10019000000,
    "total_assets": 59023000000,
    "stockholders_equity": 22703000000,
    "long_term_debt": 24937000000,
    "cash": 5412000000,
    "rd_expense": 9106000000,
    "shares_outstanding": 1241000000,
    "free_cash_flow": 9456000000,
    "debt_to_equity": 1.1,
    "operating_margin": 34.0,
    "profit_margin": 28.9
  },
  {
    "symbol": "CMCSA",
    "name": "Comcast Corp.",
    "capex": -11750000000,
    "year": 2024,
    "revenue": 123707000000,
    "sector": "Telecommunications",
    "market_cap": 130311857400,
    "market_cap_updated": "2025-07-12T17:12:41.315321",
    "earnings": 19998000000,
    "operating_income": 20672000000,
    "operating_cash_flow": 33643000000,
    "total_assets": 272631000000,
    "stockholders_equity": 96903000000,
    "cash": 9481000000,
    "free_cash_flow": 21893000000,
    "operating_margin": 16.7,
    "profit_margin": 16.2
  },
  {
    "symbol": "LOW",
    "name": "Lowe's Companies Inc.",
    "capex": -2213000000,
    "year": 2024,
    "revenue": 86286000000,
    "sector": "Consumer Discretionary",
    "market_cap": 114842310000,
    "market_cap_updated": "2026-07-20T22:47:55",
    "earnings": 6654000000,
    "operating_income": 10153000000,
    "gross_profit": 28885000000,
    "operating_cash_flow": 9864000000,
    "total_assets": 54144000000,
    "total_liabilities": 64061000000,
    "stockholders_equity": -9917000000,
    "long_term_debt": 39819000000,
    "cash": 982000000,
    "shares_outstanding": 561000000,
    "free_cash_flow": 7651000000,
    "operating_margin": 11.8,
    "profit_margin": 7.7
  },
  {
    "symbol": "ADP",
    "name": "Automatic Data Processing Inc.",
    "capex": -800000000,
    "year": 2024,
    "revenue": 20560900000,
    "sector": "Technology",
    "market_cap": 103448772000,
    "market_cap_updated": "2026-07-20T22:47:55",
    "earnings": 4079700000,
    "gross_profit": 1309600000,
    "operating_cash_flow": 4939700000,
    "total_assets": 53369300000,
    "total_liabilities": 47181300000,
    "stockholders_equity": 6188000000,
    "long_term_debt": 37000000,
    "cash": 3347800000,
    "rd_expense": 988600000,
    "shares_outstanding": 405300000,
    "free_cash_flow": 4139700000,
    "debt_to_equity": 0.01,
    "profit_margin": 19.8
  },
  {
    "symbol": "COP",
    "name": "ConocoPhillips",
    "capex": -8500000000,
    "year": 2024,
    "revenue": 51824000000,
    "sector": "Energy",
    "market_cap": 120699020100,
    "market_cap_updated": "2025-07-12T17:12:47.928230",
    "earnings": 7988000000,
    "operating_cash_flow": 19796000000,
    "total_assets": 121939000000,
    "total_liabilities": 57452000000,
    "stockholders_equity": 64487000000,
    "long_term_debt": 16147000000,
    "cash": 6497000000,
    "rd_expense": 78000000,
    "free_cash_flow": 11296000000,
    "debt_to_equity": 0.25,
    "profit_margin": 15.4
  },
  {
    "symbol": "SBUX",
    "name": "Starbucks Corp.",
    "capex": -2305500000,
    "year": 2024,
    "revenue": 37184400000,
    "sector": "Consumer Discretionary",
    "market_cap": 119158489000,
    "market_cap_updated": "2026-07-20T22:47:55",
    "earnings": 1856400000,
    "operating_income": 2936600000,
    "operating_cash_flow": 4747500000,
    "total_assets": 32019700000,
    "total_liabilities": 40108900000,
    "stockholders_equity": -8096600000,
    "long_term_debt": 16074800000,
    "cash": 6455700000,
    "shares_outstanding": 1136900000,
    "free_cash_flow": 2442000000,
    "operating_margin": 7.9,
    "profit_margin": 5.0
  },
  {
    "symbol": "NKE",
    "name": "Nike Inc.",
    "capex": -684000000,
    "year": 2024,
    "revenue": 46398000000,
    "sector": "Consumer Discretionary",
    "market_cap": 107201211877,
    "market_cap_updated": "2025-07-12T17:12:57.749420",
    "earnings": 3108000000,
    "gross_profit": 19911000000,
    "operating_cash_flow": 2868000000,
    "total_assets": 38410000000,
    "stockholders_equity": 14865000000,
    "long_term_debt": 7942000000,
    "cash": 7563000000,
    "free_cash_flow": 2184000000,
    "debt_to_equity": 0.53,
    "profit_margin": 6.7
  },
  {
    "symbol": "MMC",
    "name": "Marsh & McLennan Companies Inc.",
    "capex": -316000000,
    "year": 2024,
    "revenue": 24458000000,
    "sector": "Financials",
    "market_cap": 98759740000,
    "market_cap_updated": "2025-10-04T17:31:44",
    "earnings": 4060000000,
    "operating_income": 5817000000,
    "operating_cash_flow": 4302000000,
    "total_assets": 56481000000,
    "long_term_debt": 19947000000,
    "cash": 2398000000,
    "shares_outstanding": 491000000,
    "free_cash_flow": 3986000000,
    "operating_margin": 23.8,
    "profit_margin": 16.6
  },
  {
    "symbol": "ICE",
    "name": "Intercontinental Exchange Inc.",
    "capex": -373000000,
    "year": 2024,
    "revenue": 12640000000,
    "sector": "Financials",
    "market_cap": 80270190000,
    "market_cap_updated": "2026-07-20T22:47:56",
    "earnings": 3315000000,
    "operating_income": 4929000000,
    "operating_cash_flow": 4662000000,
    "total_assets": 136887000000,
    "total_liabilities": 107896000000,
    "stockholders_equity": 28915000000,
    "long_term_debt": 18122000000,
    "cash": 837000000,
    "shares_outstanding": 567000000,
    "free_cash_flow": 4289000000,
    "debt_to_equity": 0.63,
    "operating_margin": 39.0,
    "profit_margin": 26.2
  },
  {
    "symbol": "INTC",
    "name": "Intel Corporation",
    "capex": -14646000000,
    "year": 2024,
    "revenue": 52853000000,
    "sector": "Technology",
    "market_cap": 484717640000,
    "market_cap_updated": "2026-07-20T22:47:56",
    "earnings": -267000000,
    "operating_income": -2214000000,
    "gross_profit": 18375000000,
    "operating_cash_flow": 9697000000,
    "total_assets": 211429000000,
    "stockholders_equity": 114281000000,
    "long_term_debt": 46585000000,
    "cash": 14265000000,
    "rd_expense": 13774000000,
    "shares_outstanding": 4994000000,
    "free_cash_flow": -4949000000,
    "debt_to_equity": 0.41,
    "operating_margin": -4.2,
    "profit_margin": -0.5
  },
  {
    "symbol": "SO",
    "name": "Southern Co.",
    "capex": -12737000000,
    "year": 2024,
    "revenue": 29553000000,
    "sector": "Utilities",
    "market_cap": 101838899600,
    "market_cap_updated": "2025-07-12T17:13:14.983077",
    "earnings": 4341000000,
    "operating_income": 7285000000,
    "operating_cash_flow": 9802000000,
    "total_assets": 155720000000,
    "total_liabilities": 116853000000,
    "stockholders_equity": 36016000000,
    "cash": 1639000000,
    "free_cash_flow": -2935000000,
    "operating_margin": 24.7,
    "profit_margin": 14.7
  },
  {
    "symbol": "CME",
    "name": "CME Group Inc.",
    "capex": -83500000,
    "year": 2024,
    "revenue": 6520600000,
    "sector": "Financials",
    "market_cap": 99126728480,
    "market_cap_updated": "2025-07-12T17:13:12.858146",
    "earnings": 4072200000,
    "operating_income": 4229500000,
    "operating_cash_flow": 4277100000,
    "total_assets": 198424200000,
    "total_liabilities": 169696000000,
    "stockholders_equity": 28728200000,
    "cash": 4416900000,
    "free_cash_flow": 4193600000,
    "operating_margin": 64.9,
    "profit_margin": 62.5
  },
  {
    "symbol": "BMY",
    "name": "Bristol-Myers Squibb Co.",
    "capex": -1311000000,
    "year": 2024,
    "revenue": 48194000000,
    "sector": "Healthcare",
    "market_cap": 95363848800,
    "market_cap_updated": "2025-07-12T17:13:00.977699",
    "earnings": 7054000000,
    "gross_profit": 30745000000,
    "operating_cash_flow": 14156000000,
    "total_assets": 90038000000,
    "total_liabilities": 71533000000,
    "stockholders_equity": 18473000000,
    "long_term_debt": 44827000000,
    "cash": 10209000000,
    "rd_expense": 9951000000,
    "free_cash_flow": 12845000000,
    "debt_to_equity": 2.43,
    "profit_margin": 14.6
  },
  {
    "symbol": "DUK",
    "name": "Duke Energy Corp.",
    "capex": -14024000000,
    "year": 2024,
    "revenue": 19624000000,
    "sector": "Utilities",
    "market_cap": 97911300000,
    "market_cap_updated": "2026-07-20T22:47:57",
    "earnings": 4968000000,
    "operating_income": 8626000000,
    "operating_cash_flow": 12330000000,
    "total_assets": 195736000000,
    "stockholders_equity": 51842000000,
    "long_term_debt": 87212000000,
    "cash": 245000000,
    "shares_outstanding": 778000000,
    "free_cash_flow": -1694000000,
    "debt_to_equity": 1.68,
    "operating_margin": 44.0,
    "profit_margin": 25.3
  },
  {
    "symbol": "MCO",
    "name": "Moody's Corp.",
    "capex": -326000000,
    "year": 2024,
    "revenue": 7718000000,
    "sector": "Financials",
    "market_cap": 89865447000,
    "market_cap_updated": "2025-07-12T17:13:19.462488",
    "earnings": 2459000000,
    "operating_income": 3351000000,
    "operating_cash_flow": 2901000000,
    "total_assets": 15830000000,
    "total_liabilities": 11625000000,
    "stockholders_equity": 4054000000,
    "long_term_debt": 6994000000,
    "cash": 2384000000,
    "rd_expense": 51100000,
    "free_cash_flow": 2575000000,
    "debt_to_equity": 1.73,
    "operating_margin": 43.4,
    "profit_margin": 31.9
  },
  {
    "symbol": "MDLZ",
    "name": "Mondelez International Inc.",
    "capex": -1279000000,
    "year": 2024,
    "revenue": 38537000000,
    "sector": "Consumer Staples",
    "market_cap": 86986007600,
    "market_cap_updated": "2025-07-12T17:13:07.515957",
    "earnings": 2451000000,
    "operating_income": 3548000000,
    "gross_profit": 10935000000,
    "operating_cash_flow": 4514000000,
    "total_assets": 71487000000,
    "total_liabilities": 45596000000,
    "stockholders_equity": 25838000000,
    "long_term_debt": 15875000000,
    "cash": 4475000000,
    "rd_expense": 400000000,
    "free_cash_flow": 3235000000,
    "debt_to_equity": 0.61,
    "operating_margin": 9.2,
    "profit_margin": 6.4
  },
  {
    "symbol": "SHW",
    "name": "Sherwin-Williams Co.",
    "capex": -125162000,
    "year": 2024,
    "revenue": 23574300000,
    "sector": "Materials",
    "market_cap": 80155720000,
    "market_cap_updated": "2026-07-20T22:47:57",
    "earnings": 2568500000,
    "operating_income": 4161700000,
    "gross_profit": 11515500000,
    "operating_cash_flow": 3451600000,
    "total_assets": 25901700000,
    "stockholders_equity": 4598300000,
    "long_term_debt": 9670800000,
    "cash": 207200000,
    "rd_expense": 51922000,
    "shares_outstanding": 247700000,
    "free_cash_flow": 3326438000,
    "debt_to_equity": 2.1,
    "operating_margin": 17.7,
    "profit_margin": 10.9
  },
  {
    "symbol": "UPS",
    "name": "United Parcel Service Inc.",
    "capex": -3685000000,
    "year": 2024,
    "revenue": 88661000000,
    "sector": "Industrials",
    "market_cap": 85755211484,
    "market_cap_updated": "2025-07-12T17:13:02.113940",
    "earnings": 5572000000,
    "operating_income": 7867000000,
    "operating_cash_flow": 8450000000,
    "total_assets": 73090000000,
    "stockholders_equity": 16227000000,
    "long_term_debt": 23585000000,
    "cash": 5887000000,
    "free_cash_flow": 4765000000,
    "debt_to_equity": 1.45,
    "operating_margin": 8.9,
    "profit_margin": 6.3
  },
  {
    "symbol": "MMM",
    "name": "3M Co.",
    "capex": -910000000,
    "year": 2024,
    "revenue": 24948000000,
    "sector": "Industrials",
    "market_cap": 84372712533,
    "market_cap_updated": "2026-07-20T22:47:58",
    "earnings": 3250000000,
    "operating_income": 4629000000,
    "operating_cash_flow": 2306000000,
    "total_assets": 37733000000,
    "total_liabilities": 32986000000,
    "stockholders_equity": 4702000000,
    "long_term_debt": 12602000000,
    "cash": 2398000000,
    "rd_expense": 700000000,
    "shares_outstanding": 530279131,
    "free_cash_flow": 1396000000,
    "debt_to_equity": 2.68,
    "operating_margin": 18.6,
    "profit_margin": 13.0
  },
  {
    "symbol": "CVS",
    "name": "CVS Health Corp.",
    "capex": -2832000000,
    "year": 2024,
    "revenue": 193919000000,
    "sector": "Healthcare",
    "market_cap": 136772310000,
    "market_cap_updated": "2026-07-20T22:47:58",
    "earnings": 1768000000,
    "operating_income": 4660000000,
    "gross_profit": 28545000000,
    "operating_cash_flow": 10639000000,
    "total_assets": 253538000000,
    "total_liabilities": 178156000000,
    "stockholders_equity": 75214000000,
    "long_term_debt": 73429000000,
    "cash": 8453000000,
    "shares_outstanding": 1271000000,
    "free_cash_flow": 7807000000,
    "debt_to_equity": 0.98,
    "operating_margin": 2.4,
    "profit_margin": 0.9
  },
  {
    "symbol": "GD",
    "name": "General Dynamics Corp.",
    "capex": -1161000000,
    "year": 2024,
    "revenue": 52550000000,
    "sector": "Industrials",
    "market_cap": 100206444685,
    "market_cap_updated": "2026-07-20T22:47:58",
    "earnings": 4210000000,
    "operating_income": 5356000000,
    "operating_cash_flow": 5120000000,
    "total_assets": 57249000000,
    "stockholders_equity": 25622000000,
    "long_term_debt": 8074000000,
    "cash": 2333000000,
    "rd_expense": 1607000000,
    "shares_outstanding": 270389759,
    "free_cash_flow": 3959000000,
    "debt_to_equity": 0.32,
    "operating_margin": 10.2,
    "profit_margin": 8.0
  },
  {
    "symbol": "EMR",
    "name": "Emerson Electric Co.",
    "capex": -431000000,
    "year": 2024,
    "revenue": 18016000000,
    "sector": "Industrials",
    "market_cap": 76867224000,
    "market_cap_updated": "2026-07-20T22:47:58",
    "earnings": 2293000000,
    "gross_profit": 9519000000,
    "operating_cash_flow": 3098000000,
    "total_assets": 41964000000,
    "stockholders_equity": 20282000000,
    "long_term_debt": 8924000000,
    "cash": 2354000000,
    "rd_expense": 771000000,
    "shares_outstanding": 562800000,
    "free_cash_flow": 2667000000,
    "debt_to_equity": 0.44,
    "profit_margin": 12.7
  },
  {
    "symbol": "PNC",
    "name": "PNC Financial Services Group Inc.",
    "capex": -1100000000,
    "year": 2024,
    "revenue": 19211000000,
    "sector": "Financials",
    "market_cap": 130823220000,
    "market_cap_updated": "2026-07-20T22:47:59",
    "earnings": 6997000000,
    "operating_cash_flow": 4384000000,
    "total_assets": 573572000000,
    "total_liabilities": 512936000000,
    "stockholders_equity": 60585000000,
    "long_term_debt": 57101000000,
    "cash": 45283000000,
    "shares_outstanding": 523000000,
    "free_cash_flow": 3284000000,
    "debt_to_equity": 0.94,
    "profit_margin": 36.4
  },
  {
    "symbol": "AON",
    "name": "Aon PLC",
    "capex": -263000000,
    "year": 2024,
    "revenue": 17181000000,
    "sector": "Financials",
    "market_cap": 97878044000,
    "market_cap_updated": "2026-07-20T22:47:59",
    "earnings": 3695000000,
    "operating_income": 4344000000,
    "operating_cash_flow": 3481000000,
    "total_assets": 50784000000,
    "total_liabilities": 41236000000,
    "stockholders_equity": 9352000000,
    "long_term_debt": 15249000000,
    "cash": 1195000000,
    "shares_outstanding": 269800000,
    "free_cash_flow": 3218000000,
    "debt_to_equity": 1.63,
    "operating_margin": 25.3,
    "profit_margin": 21.5
  },
  {
    "symbol": "ITW",
    "name": "Illinois Tool Works Inc.",
    "capex": -419000000,
    "year": 2024,
    "revenue": 16044000000,
    "sector": "Industrials",
    "market_cap": 78409734000,
    "market_cap_updated": "2026-07-20T22:47:59",
    "earnings": 3066000000,
    "operating_income": 4216000000,
    "operating_cash_flow": 3126000000,
    "total_assets": 16148000000,
    "long_term_debt": 7682000000,
    "cash": 851000000,
    "rd_expense": 302000000,
    "shares_outstanding": 288600000,
    "free_cash_flow": 2707000000,
    "operating_margin": 26.3,
    "profit_margin": 19.1
  },
  {
    "symbol": "CMG",
    "name": "Chipotle Mexican Grill Inc.",
    "capex": -666336000,
    "year": 2024,
    "revenue": 11925601000,
    "sector": "Consumer Discretionary",
    "market_cap": 75452160000,
    "market_cap_updated": "2025-07-12T17:13:24.795586",
    "earnings": 1535761000,
    "operating_income": 1935798000,
    "operating_cash_flow": 2113926000,
    "total_assets": 8994531000,
    "total_liabilities": 6163924000,
    "stockholders_equity": 2830607000,
    "long_term_debt": 0,
    "cash": 350545000,
    "free_cash_flow": 1447590000,
    "debt_to_equity": 0.0,
    "operating_margin": 16.2,
    "profit_margin": 12.9
  },
  {
    "symbol": "USB",
    "name": "U.S. Bancorp",
    "capex": -2100000000,
    "year": 2024,
    "revenue": 28656000000,
    "sector": "Financials",
    "market_cap": 101024000000,
    "market_cap_updated": "2026-07-20T22:47:59",
    "earnings": 7570000000,
    "operating_cash_flow": 7970000000,
    "total_assets": 692345000000,
    "total_liabilities": 626694000000,
    "stockholders_equity": 65193000000,
    "long_term_debt": 39829000000,
    "cash": 8252000000,
    "shares_outstanding": 1600000000,
    "free_cash_flow": 5870000000,
    "debt_to_equity": 0.61,
    "profit_margin": 26.4
  },
  {
    "symbol": "CL",
    "name": "Colgate-Palmolive Co.",
    "capex": -696000000,
    "year": 2024,
    "revenue": 20382000000,
    "sector": "Consumer Staples",
    "market_cap": 73657949441,
    "market_cap_updated": "2026-07-20T22:47:59",
    "earnings": 2132000000,
    "operating_income": 3306000000,
    "gross_profit": 12251000000,
    "operating_cash_flow": 4198000000,
    "total_assets": 16330000000,
    "total_liabilities": 15965000000,
    "stockholders_equity": 54000000,
    "long_term_debt": 7839000000,
    "cash": 1288000000,
    "rd_expense": 366000000,
    "shares_outstanding": 801239524,
    "free_cash_flow": 3502000000,
    "debt_to_equity": 145.17,
    "operating_margin": 16.2,
    "profit_margin": 10.5
  },
  {
    "symbol": "PYPL",
    "name": "PayPal Holdings Inc.",
    "capex": -852000000,
    "year": 2024,
    "revenue": 17772000000,
    "sector": "Financial Services",
    "market_cap": 52274400000,
    "market_cap_updated": "2026-07-20T22:48:00",
    "earnings": 5233000000,
    "operating_income": 6065000000,
    "operating_cash_flow": 6416000000,
    "total_assets": 80173000000,
    "total_liabilities": 59917000000,
    "stockholders_equity": 20256000000,
    "long_term_debt": 9987000000,
    "cash": 8049000000,
    "rd_expense": 1071000000,
    "shares_outstanding": 920000000,
    "free_cash_flow": 5564000000,
    "debt_to_equity": 0.49,
    "operating_margin": 34.1,
    "profit_margin": 29.4
  },
  {
    "symbol": "EOG",
    "name": "EOG Resources Inc.",
    "capex": -4900000000,
    "year": 2024,
    "revenue": 22632000000,
    "sector": "Energy",
    "market_cap": 38324558880,
    "market_cap_updated": "2026-07-20T22:48:00",
    "earnings": 4980000000,
    "operating_income": 6385000000,
    "operating_cash_flow": 10044000000,
    "total_assets": 51799000000,
    "stockholders_equity": 29833000000,
    "long_term_debt": 7909000000,
    "cash": 3396000000,
    "shares_outstanding": 271632000,
    "free_cash_flow": 5144000000,
    "debt_to_equity": 0.27,
    "operating_margin": 28.2,
    "profit_margin": 22.0
  },
  {
    "symbol": "APD",
    "name": "Air Products and Chemicals Inc.",
    "capex": -7022600000,
    "year": 2024,
    "revenue": 12037300000,
    "sector": "Materials",
    "market_cap": 66026354377,
    "market_cap_updated": "2026-07-20T22:48:00",
    "earnings": -394500000,
    "operating_income": -877000000,
    "gross_profit": 2998200000,
    "operating_cash_flow": 1753200000,
    "total_assets": 41059500000,
    "total_liabilities": 23709700000,
    "stockholders_equity": 15024900000,
    "long_term_debt": 5289400000,
    "cash": 1856000000,
    "rd_expense": 96300000,
    "shares_outstanding": 222588256,
    "free_cash_flow": -5269400000,
    "debt_to_equity": 0.35,
    "operating_margin": -7.3,
    "profit_margin": -3.3
  },
  {
    "symbol": "NSC",
    "name": "Norfolk Southern Corp.",
    "capex": -2204000000,
    "year": 2024,
    "revenue": 12180000000,
    "sector": "Industrials",
    "market_cap": 75174201544,
    "market_cap_updated": "2026-07-20T22:48:00",
    "earnings": 2873000000,
    "operating_income": 4356000000,
    "operating_cash_flow": 4361000000,
    "total_assets": 45236000000,
    "total_liabilities": 29689000000,
    "stockholders_equity": 15547000000,
    "long_term_debt": 9736000000,
    "cash": 1530000000,
    "shares_outstanding": 224420699,
    "free_cash_flow": 2157000000,
    "debt_to_equity": 0.63,
    "operating_margin": 35.8,
    "profit_margin": 23.6
  },
  {
    "symbol": "TFC",
    "name": "Truist Financial Corp.",
    "capex": -564000000,
    "year": 2024,
    "revenue": 20582000000,
    "sector": "Financials",
    "market_cap": 64385970000,
    "market_cap_updated": "2026-07-20T22:48:00",
    "earnings": 5307000000,
    "operating_cash_flow": 5739000000,
    "total_assets": 547538000000,
    "total_liabilities": 482349000000,
    "long_term_debt": 41963000000,
    "cash": 20295000000,
    "shares_outstanding": 1262470000,
    "free_cash_flow": 5175000000,
    "profit_margin": 25.8,
    "stockholders_equity": 65189000000,
    "debt_to_equity": 0.64
  },
  {
    "symbol": "FDX",
    "name": "FedEx Corp.",
    "capex": -5400000000,
    "year": 2024,
    "revenue": 87926000000,
    "sector": "Industrials",
    "market_cap": 56559739940,
    "market_cap_updated": "2025-07-12T17:13:21.608416",
    "earnings": 4092000000,
    "operating_income": 5217000000,
    "operating_cash_flow": 7036000000,
    "total_assets": 87627000000,
    "stockholders_equity": 28074000000,
    "long_term_debt": 19899000000,
    "cash": 5502000000,
    "free_cash_flow": 1636000000,
    "debt_to_equity": 0.71,
    "operating_margin": 5.9,
    "profit_margin": 4.7
  },
  {
    "symbol": "SLB",
    "name": "Schlumberger NV",
    "capex": -1694000000,
    "year": 2024,
    "revenue": 35708000000,
    "sector": "Energy",
    "market_cap": 69368427589,
    "market_cap_updated": "2026-07-20T22:48:01",
    "earnings": 3374000000,
    "operating_income": 6523000000,
    "operating_cash_flow": 6489000000,
    "total_assets": 54868000000,
    "total_liabilities": 27577000000,
    "stockholders_equity": 26109000000,
    "long_term_debt": 9742000000,
    "cash": 3130000000,
    "rd_expense": 709000000,
    "shares_outstanding": 1495331485,
    "free_cash_flow": 4795000000,
    "debt_to_equity": 0.37,
    "operating_margin": 18.3,
    "profit_margin": 9.4
  },
  {
    "symbol": "TGT",
    "name": "Target Corp.",
    "capex": -3727000000,
    "year": 2024,
    "revenue": 104780000000,
    "sector": "Consumer Discretionary",
    "market_cap": 63211961703,
    "market_cap_updated": "2026-07-20T22:48:01",
    "earnings": 3705000000,
    "operating_income": 5117000000,
    "gross_profit": 20754000000,
    "operating_cash_flow": 6562000000,
    "total_assets": 59490000000,
    "stockholders_equity": 16165000000,
    "long_term_debt": 14398000000,
    "cash": 250000000,
    "shares_outstanding": 452840187,
    "free_cash_flow": 2835000000,
    "debt_to_equity": 0.89,
    "operating_margin": 4.9,
    "profit_margin": 3.5
  },
  {
    "symbol": "CNC",
    "name": "Centene Corp.",
    "capex": -767000000,
    "year": 2024,
    "revenue": 174581000000,
    "sector": "Healthcare",
    "market_cap": 32377280880,
    "market_cap_updated": "2026-07-20T22:48:01",
    "earnings": -6674000000,
    "operating_income": -7623000000,
    "gross_profit": 14209000000,
    "operating_cash_flow": 5088000000,
    "total_assets": 76747000000,
    "total_liabilities": 56691000000,
    "stockholders_equity": 19953000000,
    "long_term_debt": 17493000000,
    "cash": 17888000000,
    "shares_outstanding": 491757000,
    "free_cash_flow": 4321000000,
    "debt_to_equity": 0.88,
    "operating_margin": -4.4,
    "profit_margin": -3.8
  }
]